{
  "required": true,
  "package": "com.bawnorton.allthetrims.mixin.client",
  "compatibilityLevel": "JAVA_17",
  "plugin": "com.bawnorton.allthetrims.AllTheTrimsMixinConfigPlugin",
  "client": [
    "ArmorFeatureRendererMixin",
    "ArmorTrimMaterialMixin",
    "BakedModelManagerMixin",
    "ExtraElytraFeatureRendererMixin",
    "ItemModelGeneratorMixin",
    "NamespaceResourceManagerMixin",
    "PalettedPermutationsAtlasSourceMixin"
  ],
  "injectors": {
    "defaultRequire": 1
  },
  "mixins": [
  ]
}